wzp/__init__.py
wzp/main.py
package_wzp-0.1.3.dist-info/LICENSE.txt
package_wzp-0.1.3.dist-info/METADATA
package_wzp-0.1.3.dist-info/WHEEL
package_wzp-0.1.3.dist-info/top_level.txt
package_wzp-0.1.3.dist-info/RECORD
